jctlfmt/__init__.py
jctlfmt-1.4.0.dist-info/licenses/LICENSE
jctlfmt-1.4.0.dist-info/METADATA
jctlfmt-1.4.0.dist-info/WHEEL
jctlfmt-1.4.0.dist-info/top_level.txt
jctlfmt-1.4.0.dist-info/RECORD
