Metadata-Version: 2.4
Name: jctlfmt
Version: 1.4.0
Summary: Python Journalctl parsing and formatting library
Home-page: https://github.com/dmotte/jctlfmt
Author: dmotte
License: MIT
Keywords: fmt journal parsing log text formatting systemd format logs msg message journald messages filtering journalctl systemd-journald jctl
Classifier: Intended Audience :: System Administrators
Classifier: Environment :: Console
Classifier: Natural Language :: English
Classifier: License :: OSI Approved :: MIT License
Classifier: Programming Language :: Python
Classifier: Programming Language :: Python :: 3
Classifier: Programming Language :: Python :: 3 :: Only
Classifier: Programming Language :: Python :: 3.9
Classifier: Topic :: Utilities
Requires-Python: >=3.9.1
License-File: LICENSE
Dynamic: license-file
